dj_admins_setting.py
dj_admins_setting-1.0.0.dist-info/LICENSE
dj_admins_setting-1.0.0.dist-info/METADATA
dj_admins_setting-1.0.0.dist-info/WHEEL
dj_admins_setting-1.0.0.dist-info/top_level.txt
dj_admins_setting-1.0.0.dist-info/RECORD
