Metadata-Version: 2.1
Name: dj-admins-setting
Version: 1.0.0
Summary: Use a string to configure the admins emails setting in your Django Application.
Home-page: https://github.com/hernantz/dj-admins-setting
Author: Hernan Lozano
Author-email: hernantz@gmail.com
License: BSD
Platform: any
Classifier: Environment :: Web Environment
Classifier: Intended Audience :: Developers
Classifier: License :: OSI Approved :: BSD License
Classifier: Operating System :: OS Independent
Classifier: Programming Language :: Python
Classifier: Programming Language :: Python :: 2
Classifier: Programming Language :: Python :: 3
Classifier: Topic :: Internet :: WWW/HTTP :: Dynamic Content
Classifier: Topic :: Software Development :: Libraries :: Python Modules
